ogzoengine/__init__.py
ogzoengine/main.py
ogzoengine-2.0.dist-info/METADATA
ogzoengine-2.0.dist-info/WHEEL
ogzoengine-2.0.dist-info/top_level.txt
ogzoengine-2.0.dist-info/RECORD
