Metadata-Version: 2.1
Name: ogzoengine
Version: 2.0
Summary: basic pygame engine
Author: Coguz
License: Apache License, Version 2.0
Classifier: License :: OSI Approved :: MIT License
Classifier: Programming Language :: Python :: 3.10
Classifier: Operating System :: OS Independent
Requires-Python: >=3.10
Requires-Dist: pygame >=2.0.1
Requires-Dist: keyboard >=0.13.3
Provides-Extra: dev
Requires-Dist: pytest >=7.0 ; extra == 'dev'
Requires-Dist: twine >=4.0.2 ; extra == 'dev'
Requires-Dist: some-other-dependency >=1.0 ; extra == 'dev'
